sales_agent_mcp/__init__.py
sales_agent_mcp/agents.py
sales_agent_mcp/config.py
sales_agent_mcp/server.py
sales_agent_mcp-0.1.0.dist-info/METADATA
sales_agent_mcp-0.1.0.dist-info/WHEEL
sales_agent_mcp-0.1.0.dist-info/entry_points.txt
sales_agent_mcp-0.1.0.dist-info/licenses/LICENSE
sales_agent_mcp-0.1.0.dist-info/RECORD
