Metadata-Version: 2.4
Name: sales-agent-mcp
Version: 0.1.0
Summary: AI-powered multi-agent sales email generation MCP server using OpenAI Agents SDK
Project-URL: Homepage, https://github.com/mmaun/sales-agent
Project-URL: Documentation, https://github.com/mmaun/sales-agent#readme
Project-URL: Repository, https://github.com/mmaun/sales-agent
Project-URL: Issues, https://github.com/mmaun/sales-agent/issues
Author-email: Mani Maun <manny.maun@biznez.co.uk>
License: MIT
License-File: LICENSE
Keywords: ai-agents,email-generation,mcp,model-context-protocol,openai-agents,sales-automation,sendgrid
Classifier: Development Status :: 4 - Beta
Classifier: Intended Audience :: Developers
Classifier: Intended Audience :: End Users/Desktop
Classifier: License :: OSI Approved :: MIT License
Classifier: Programming Language :: Python :: 3.11
Classifier: Programming Language :: Python :: 3.12
Classifier: Topic :: Communications :: Email
Classifier: Topic :: Office/Business
Classifier: Topic :: Scientific/Engineering :: Artificial Intelligence
Requires-Python: >=3.11
Requires-Dist: httpx>=0.27.0
Requires-Dist: mcp>=1.18.0
Requires-Dist: openai-agents>=0.4.0
Requires-Dist: python-dotenv>=1.0.0
Requires-Dist: sendgrid>=6.11.0
Provides-Extra: dev
Requires-Dist: black>=24.0.0; extra == 'dev'
Requires-Dist: pytest-asyncio>=0.23.0; extra == 'dev'
Requires-Dist: pytest>=8.0.0; extra == 'dev'
Requires-Dist: ruff>=0.3.0; extra == 'dev'
